ezarduino/__init__.py
ezarduino/errors.py
ezarduino/serial.py
ezarduino-1.0.0.dist-info/LICENSE
ezarduino-1.0.0.dist-info/METADATA
ezarduino-1.0.0.dist-info/WHEEL
ezarduino-1.0.0.dist-info/top_level.txt
ezarduino-1.0.0.dist-info/RECORD
