Metadata-Version: 2.1
Name: ezarduino
Version: 1.0.0
Summary: A library designed to facilitate communication between Python and Arduino devices.
Home-page: https://github.com/cr4t3/ezarduino
Author: Crate
Author-email: Crate <crate.arg@proton.me>
License: MIT
Project-URL: Homepage, https://github.com/cr4t3/ezarduino
Project-URL: Issues, https://github.com/cr4t3/ezarduino/issues
Classifier: Programming Language :: Python :: 3.9
Classifier: Programming Language :: Python :: 3.10
Classifier: Programming Language :: Python :: 3.11
Classifier: Programming Language :: Python :: 3.12
Classifier: Programming Language :: Python :: 3.13
Classifier: License :: OSI Approved :: MIT License
Classifier: Operating System :: OS Independent
Requires-Python: >=3.9
License-File: LICENSE
Requires-Dist: pyserial>=3.5
